{
  "variants": [
    {
      "id": "AU-01",
      "name": "TerraFirma AutoCultivator T-300 Silver",
      "sku": "AU-01-SI",
      "price": 1000,
      "image": "/cdn/img/product/[size]/AU-01-SI.webp",
      "inventory": 8
    },
    {
      "id": "AU-02",
      "name": "SmartFarm Titan Sunset Copper",
      "sku": "AU-02-OG",
      "price": 4100,
      "image": "/cdn/img/product/[size]/AU-02-OG.webp",
      "inventory": 4
    },
    {
      "id": "AU-02",
      "name": "SmartFarm Titan Cosmic Sapphire",
      "sku": "AU-02-BL",
      "price": 4000,
      "image": "/cdn/img/product/[size]/AU-02-BL.webp",
      "inventory": 3
    },
    {
      "id": "AU-02",
      "name": "SmartFarm Titan Verdant Shadow",
      "sku": "AU-02-GG",
      "price": 4000,
      "image": "/cdn/img/product/[size]/AU-02-GG.webp",
      "inventory": 6
    },
    {
      "id": "AU-03",
      "name": "FutureHarvest Navigator Turquoise Titan",
      "sku": "AU-03-TQ",
      "price": 1600,
      "image": "/cdn/img/product/[size]/AU-03-TQ.webp",
      "inventory": 9
    },
    {
      "id": "AU-03",
      "name": "FutureHarvest Navigator Majestic Violet",
      "sku": "AU-03-PL",
      "price": 1700,
      "image": "/cdn/img/product/[size]/AU-03-PL.webp",
      "inventory": 7
    },
    {
      "id": "AU-03",
      "name": "FutureHarvest Navigator Scarlet Dynamo",
      "sku": "AU-03-RD",
      "price": 1900,
      "image": "/cdn/img/product/[size]/AU-03-RD.webp",
      "inventory": 8
    },
    {
      "id": "AU-03",
      "name": "FutureHarvest Navigator Sunbeam Yellow",
      "sku": "AU-03-YE",
      "price": 1800,
      "image": "/cdn/img/product/[size]/AU-03-YE.webp",
      "inventory": 3
    },
    {
      "id": "AU-04",
      "name": "Sapphire Sunworker 460R Ruby Red",
      "sku": "AU-04-RD",
      "price": 8700,
      "image": "/cdn/img/product/[size]/AU-04-RD.webp",
      "inventory": 9
    },
    {
      "id": "AU-04",
      "name": "Sapphire Sunworker 460R Midnight Onyx",
      "sku": "AU-04-BK",
      "price": 8500,
      "image": "/cdn/img/product/[size]/AU-04-BK.webp",
      "inventory": 8
    },
    {
      "id": "AU-05",
      "name": "EcoGrow Crop Commander Zestful Horizon",
      "sku": "AU-05-ZH",
      "price": 3400,
      "image": "/cdn/img/product/[size]/AU-05-ZH.webp",
      "inventory": 8
    },
    {
      "id": "AU-06",
      "name": "FarmFleet Sovereign Canary Zenith",
      "sku": "AU-06-CZ",
      "price": 2200,
      "image": "/cdn/img/product/[size]/AU-06-CZ.webp",
      "inventory": 3
    },
    {
      "id": "AU-06",
      "name": "FarmFleet Sovereign Minted Jade",
      "sku": "AU-06-MT",
      "price": 2100,
      "image": "/cdn/img/product/[size]/AU-06-MT.webp",
      "inventory": 5
    },
    {
      "id": "AU-07",
      "name": "Verde Voyager Glacial Mint",
      "sku": "AU-07-MT",
      "price": 4000,
      "image": "/cdn/img/product/[size]/AU-07-MT.webp",
      "inventory": 4
    },
    {
      "id": "AU-07",
      "name": "Verde Voyager Sunbeam Yellow",
      "sku": "AU-07-YE",
      "price": 5000,
      "image": "/cdn/img/product/[size]/AU-07-YE.webp",
      "inventory": 9
    },
    {
      "id": "AU-08",
      "name": "Field Pioneer Polar White",
      "sku": "AU-08-WH",
      "price": 4500,
      "image": "/cdn/img/product/[size]/AU-08-WH.webp",
      "inventory": 4
    },
    {
      "id": "CL-01",
      "name": "Heritage Workhorse Verdant Field",
      "sku": "CL-01-GR",
      "price": 5700,
      "image": "/cdn/img/product/[size]/CL-01-GR.webp",
      "inventory": 8
    },
    {
      "id": "CL-01",
      "name": "Heritage Workhorse Stormy Sky",
      "sku": "CL-01-GY",
      "price": 6200,
      "image": "/cdn/img/product/[size]/CL-01-GY.webp",
      "inventory": 7
    },
    {
      "id": "CL-02",
      "name": "Falcon Crest Farm Cerulean Classic",
      "sku": "CL-02-BL",
      "price": 2600,
      "image": "/cdn/img/product/[size]/CL-02-BL.webp",
      "inventory": 1
    },
    {
      "id": "CL-03",
      "name": "Falcon Crest Work Meadow Green",
      "sku": "CL-03-GR",
      "price": 2300,
      "image": "/cdn/img/product/[size]/CL-03-GR.webp",
      "inventory": 7
    },
    {
      "id": "CL-03",
      "name": "Falcon Crest Work Rustic Rose",
      "sku": "CL-03-PI",
      "price": 2300,
      "image": "/cdn/img/product/[size]/CL-03-PI.webp",
      "inventory": 3
    },
    {
      "id": "CL-03",
      "name": "Falcon Crest Work Harvest Gold",
      "sku": "CL-03-YE",
      "price": 2300,
      "image": "/cdn/img/product/[size]/CL-03-YE.webp",
      "inventory": 6
    },
    {
      "id": "CL-04",
      "name": "Broadfield Majestic Oceanic Blue",
      "sku": "CL-04-BL",
      "price": 2200,
      "image": "/cdn/img/product/[size]/CL-04-BL.webp",
      "inventory": 6
    },
    {
      "id": "CL-04",
      "name": "Broadfield Majestic Rustic Crimson",
      "sku": "CL-04-RD",
      "price": 2200,
      "image": "/cdn/img/product/[size]/CL-04-RD.webp",
      "inventory": 3
    },
    {
      "id": "CL-04",
      "name": "Broadfield Majestic Aqua Green",
      "sku": "CL-04-TQ",
      "price": 2200,
      "image": "/cdn/img/product/[size]/CL-04-TQ.webp",
      "inventory": 0
    },
    {
      "id": "CL-05",
      "name": "Countryside Commander Pacific Teal",
      "sku": "CL-05-PT",
      "price": 2700,
      "image": "/cdn/img/product/[size]/CL-05-PT.webp",
      "inventory": 1
    },
    {
      "id": "CL-05",
      "name": "Countryside Commander Barn Red",
      "sku": "CL-05-RD",
      "price": 2700,
      "image": "/cdn/img/product/[size]/CL-05-RD.webp",
      "inventory": 1
    },
    {
      "id": "CL-06",
      "name": "Danamark Steadfast Emerald Forest",
      "sku": "CL-06-MT",
      "price": 2800,
      "image": "/cdn/img/product/[size]/CL-06-MT.webp",
      "inventory": 1
    },
    {
      "id": "CL-06",
      "name": "Danamark Steadfast Golden Wheat",
      "sku": "CL-06-YE",
      "price": 2800,
      "image": "/cdn/img/product/[size]/CL-06-YE.webp",
      "inventory": 2
    },
    {
      "id": "CL-07",
      "name": "Greenland Rover Forest Fern",
      "sku": "CL-07-GR",
      "price": 2900,
      "image": "/cdn/img/product/[size]/CL-07-GR.webp",
      "inventory": 4
    },
    {
      "id": "CL-07",
      "name": "Greenland Rover Autumn Amber",
      "sku": "CL-07-YE",
      "price": 2900,
      "image": "/cdn/img/product/[size]/CL-07-YE.webp",
      "inventory": 4
    },
    {
      "id": "CL-08",
      "name": "Holland Hamster Polder Green",
      "sku": "CL-08-GR",
      "price": 7750,
      "image": "/cdn/img/product/[size]/CL-08-GR.webp",
      "inventory": 8
    },
    {
      "id": "CL-08",
      "name": "Holland Hamster Tulip Magenta",
      "sku": "CL-08-PI",
      "price": 7900,
      "image": "/cdn/img/product/[size]/CL-08-PI.webp",
      "inventory": 3
    },
    {
      "id": "CL-09",
      "name": "TerraFirma Veneto Adriatic Blue",
      "sku": "CL-09-BL",
      "price": 2950,
      "image": "/cdn/img/product/[size]/CL-09-BL.webp",
      "inventory": 4
    },
    {
      "id": "CL-09",
      "name": "TerraFirma Veneto Tuscan Green",
      "sku": "CL-09-GR",
      "price": 2950,
      "image": "/cdn/img/product/[size]/CL-09-GR.webp",
      "inventory": 7
    },
    {
      "id": "CL-10",
      "name": "Global Gallant Sahara Dawn",
      "sku": "CL-10-SD",
      "price": 2600,
      "image": "/cdn/img/product/[size]/CL-10-SD.webp",
      "inventory": 6
    },
    {
      "id": "CL-10",
      "name": "Global Gallant Violet Vintage",
      "sku": "CL-10-VI",
      "price": 2600,
      "image": "/cdn/img/product/[size]/CL-10-VI.webp",
      "inventory": 2
    },
    {
      "id": "CL-11",
      "name": "Scandinavia Sower Baltic Blue",
      "sku": "CL-11-SK",
      "price": 3100,
      "image": "/cdn/img/product/[size]/CL-11-SK.webp",
      "inventory": 0
    },
    {
      "id": "CL-11",
      "name": "Scandinavia Sower Nordic Gold",
      "sku": "CL-11-YE",
      "price": 3100,
      "image": "/cdn/img/product/[size]/CL-11-YE.webp",
      "inventory": 3
    },
    {
      "id": "CL-12",
      "name": "Celerity Cruiser Velocity Blue",
      "sku": "CL-12-BL",
      "price": 3200,
      "image": "/cdn/img/product/[size]/CL-12-BL.webp",
      "inventory": 8
    },
    {
      "id": "CL-12",
      "name": "Celerity Cruiser Rally Red",
      "sku": "CL-12-RD",
      "price": 3200,
      "image": "/cdn/img/product/[size]/CL-12-RD.webp",
      "inventory": 8
    },
    {
      "id": "CL-13",
      "name": "Rapid Racer Speedway Blue",
      "sku": "CL-13-BL",
      "price": 7500,
      "image": "/cdn/img/product/[size]/CL-13-BL.webp",
      "inventory": 1
    },
    {
      "id": "CL-13",
      "name": "Rapid Racer Raceway Red",
      "sku": "CL-13-RD",
      "price": 7500,
      "image": "/cdn/img/product/[size]/CL-13-RD.webp",
      "inventory": 5
    },
    {
      "id": "CL-14",
      "name": "Caribbean Cruiser Emerald Grove",
      "sku": "CL-14-GR",
      "price": 2300,
      "image": "/cdn/img/product/[size]/CL-14-GR.webp",
      "inventory": 3
    },
    {
      "id": "CL-14",
      "name": "Caribbean Cruiser Ruby Fields",
      "sku": "CL-14-RD",
      "price": 2300,
      "image": "/cdn/img/product/[size]/CL-14-RD.webp",
      "inventory": 5
    },
    {
      "id": "CL-15",
      "name": "Fieldmaster Classic Vintage Pink",
      "sku": "CL-15-PI",
      "price": 6200,
      "image": "/cdn/img/product/[size]/CL-15-PI.webp",
      "inventory": 0
    },
    {
      "id": "CL-15",
      "name": "Fieldmaster Classic Sahara Dust",
      "sku": "CL-15-SD",
      "price": 6200,
      "image": "/cdn/img/product/[size]/CL-15-SD.webp",
      "inventory": 9
    }
  ]
}